quantitizer/__init__.py
quantitizer/_pq_array.py
quantitizer/cuda.py
quantitizer/exceptions.py
quantitizer/integration/__init__.py
quantitizer/integration/evaluation.py
quantitizer/integration/gensim/__init__.py
quantitizer/integration/gensim/fasttext.py
quantitizer/integration/gensim/word2vec.py
quantitizer/pretrain.py
quantitizer/utils.py
quantitizer-1.1.0.dist-info/LICENSE
quantitizer-1.1.0.dist-info/WHEEL
quantitizer-1.1.0.dist-info/METADATA
quantitizer-1.1.0.dist-info/RECORD
