Metadata-Version: 2.1
Name: quantitizer
Version: 1.1.0
Summary: This package allows to quantitize matrix to compress different ML models.
Author: CapBlood
Author-email: stalker.anonim@mail.ru
Requires-Python: >=3.8,<4.0
Classifier: Programming Language :: Python :: 3
Classifier: Programming Language :: Python :: 3.10
Classifier: Programming Language :: Python :: 3.8
Classifier: Programming Language :: Python :: 3.9
Requires-Dist: gensim (>=4.2.0,<5.0.0)
Requires-Dist: mega.py (>=1.0.8,<2.0.0)
Requires-Dist: numpy (>=1.23.0,<2.0.0)
